{"60": {"4": {"9": {"unknown": {"unknown": {"1": {"unknown": "47D"}, "2": {"unknown": "47D"}, "3": {"unknown": "47DRe"}}}}}}, "67": {"4": {"9": {"unknown": {"unknown": {"1": {"unknown": "53Ta"}, "2": {"unknown": "53Ta"}, "3": {"unknown": "53Ta"}}}}}}, "69": {"4": {"9": {"unknown": {"unknown": {"1": {"unknown": "53Ta"}, "2": {"unknown": "53Ta"}, "3": {"unknown": "53*"}}}}}}, "49*": {"1": {"9": {"unknown": {"unknown": {"1": {"unknown": "49*Ta"}, "2": {"unknown": "49*Ta"}, "3": {"unknown": "49*"}}}}}, "3": {"9": {"unknown": {"unknown": {"1": {"unknown": "49*Ta"}, "2": {"unknown": "49*Ta"}, "3": {"unknown": "49*"}}}}}, "J": {"9": {"unknown": {"unknown": {"1": {"unknown": "49*Ta"}, "2": {"unknown": "49*Ta"}, "3": {"unknown": "49*"}}}}}, "M": {"9": {"unknown": {"unknown": {"1": {"unknown": "49*Ta"}, "2": {"unknown": "49*Ta"}, "3": {"unknown": "49*"}}}}}, "2a": {"9": {"unknown": {"unknown": {"1": {"unknown": "49*Ta"}, "2": {"unknown": "49*Ta"}, "3": {"unknown": "49*"}}}}}, "2b": {"9": {"unknown": {"unknown": {"1": {"unknown": "49*Ta"}, "2": {"unknown": "49*Ta"}, "3": {"unknown": "49*"}}}}}}, "57C": {"1": {"9": {"unknown": {"unknown": {"1": {"unknown": "51"}, "2": {"unknown": "51"}, "3": {"unknown": "55"}}}}}, "3": {"9": {"unknown": {"unknown": {"1": {"unknown": "51"}, "2": {"unknown": "51Re"}, "3": {"unknown": "55"}}}}}, "4": {"9": {"unknown": {"unknown": {"1": {"unknown": "47Re"}, "2": {"unknown": "47"}, "3": {"unknown": "47"}}}}}, "J": {"9": {"unknown": {"unknown": {"1": {"unknown": "51"}, "2": {"unknown": "51"}, "3": {"unknown": "55"}}}}}, "M": {"9": {"unknown": {"unknown": {"1": {"unknown": "51"}, "2": {"unknown": "51"}, "3": {"unknown": "55"}}}}}, "2a": {"9": {"unknown": {"unknown": {"1": {"unknown": "51"}, "2": {"unknown": "51"}, "3": {"unknown": "55"}}}}}, "2b": {"9": {"unknown": {"unknown": {"1": {"unknown": "51Re"}, "2": {"unknown": "51"}, "3": {"unknown": "51"}}}}}}, "57V": {"4": {"9": {"unknown": {"unknown": {"1": {"unknown": "46MRe"}, "2": {"unknown": "46M"}, "3": {"unknown": "46MRe"}}}}}}, "59A": {"4": {"9": {"unknown": {"unknown": {"1": {"unknown": "47D"}, "2": {"unknown": "47D"}, "3": {"unknown": "47D"}}}}}}, "59S": {"4": {"9": {"unknown": {"unknown": {"1": {"unknown": "52"}, "2": {"unknown": "52Re"}, "3": {"unknown": "52Re"}}}}}}, "60*": {"4": {"9": {"unknown": {"unknown": {"1": {"unknown": "50*Re"}, "2": {"unknown": "50*"}, "3": {"unknown": "50*"}}}}}}, "60A": {"4": {"9": {"unknown": {"unknown": {"1": {"unknown": "47DRe"}, "2": {"unknown": "47D"}, "3": {"unknown": "47DRe"}}}}}}, "57Bl": {"4": {"9": {"unknown": {"Nrml": {"3": {"unknown": "47H"}}, "Shdy_Cl": {"3": {"unknown": "57Bl"}}, "unknown": {"1": {"unknown": "48"}, "2": {"unknown": "48"}}}}}}, "57VM": {"1": {"9": {"unknown": {"unknown": {"1": {"unknown": "51"}, "2": {"unknown": "51"}, "3": {"unknown": "51Re"}}}}}, "3": {"9": {"unknown": {"unknown": {"1": {"unknown": "51"}, "2": {"unknown": "51"}, "3": {"unknown": "51Re"}}}}}, "4": {"9": {"unknown": {"unknown": {"1": {"unknown": "47M"}, "2": {"unknown": "47MRe"}, "3": {"unknown": "47MRe"}}}}}, "J": {"9": {"unknown": {"unknown": {"1": {"unknown": "51"}, "2": {"unknown": "51"}, "3": {"unknown": "51Re"}}}}}, "M": {"9": {"unknown": {"unknown": {"1": {"unknown": "51"}, "2": {"unknown": "51"}, "3": {"unknown": "51Re"}}}}}, "2a": {"9": {"unknown": {"unknown": {"1": {"unknown": "51"}, "2": {"unknown": "51"}, "3": {"unknown": "51Re"}}}}}, "2b": {"9": {"unknown": {"unknown": {"1": {"unknown": "51"}, "2": {"unknown": "51"}, "3": {"unknown": "51Re"}}}}}}, "57CLä": {"1": {"9": {"unknown": {"unknown": {"1": {"unknown": "51"}, "2": {"unknown": "51"}, "3": {"unknown": "55"}}}}}, "3": {"9": {"unknown": {"unknown": {"1": {"unknown": "51Re"}, "2": {"unknown": "51"}, "3": {"unknown": "55"}}}}}, "4": {"9": {"unknown": {"unknown": {"1": {"unknown": "47Re"}, "2": {"unknown": "47Re"}, "3": {"unknown": "47"}}}}}, "J": {"9": {"unknown": {"unknown": {"1": {"unknown": "51"}, "2": {"unknown": "51"}, "3": {"unknown": "55"}}}}}, "M": {"9": {"unknown": {"unknown": {"1": {"unknown": "51"}, "2": {"unknown": "51"}, "3": {"unknown": "55"}}}}}, "2a": {"9": {"unknown": {"unknown": {"1": {"unknown": "51"}, "2": {"unknown": "51"}, "3": {"unknown": "55"}}}}}, "2b": {"9": {"unknown": {"unknown": {"1": {"unknown": "51Re"}, "2": {"unknown": "51"}, "3": {"unknown": "51"}}}}}}, "57VLä": {"4": {"9": {"unknown": {"unknown": {"1": {"unknown": "46M"}, "2": {"unknown": "46M"}, "3": {"unknown": "46MRe"}}}}}}}
